{"12119":[12119,"Floowandereeze and the Magnificent Map",6,9,"66.67%"],"12077":[12077,"Floowandereeze & Toccan",2,2,"100.0%"],"12074":[12074,"Floowandereeze & Robina",6,9,"66.67%"],"8504":[8504,"Ash Blossom & Joyous Spring",32,57,"56.14%"],"10148":[10148,"Crossout Designator",9,16,"56.25%"],"12075":[12075,"Floowandereeze & Eglen",6,9,"66.67%"],"12078":[12078,"Floowandereeze & Empen",6,6,"100.0%"],"12076":[12076,"Floowandereeze & Stri",5,6,"83.33%"],"12073":[12073,"Floowandereeze & Snowl",3,3,"100.0%"],"11306":[11306,"Pot of Prosperity",15,31,"48.39%"],"5329":[5329,"Hieratic Dragon of Gebeb",2,3,"66.67%"],"1947047":[1947047,"Hieratic Dragon of Sekh",4,5,"80.0%"],"1944751":[1944751,"Hieratic Seal of Release",0,1,"0.0%"],"5334":[5334,"Hieratic Dragon of Su",4,6,"66.67%"],"1947069":[1947069,"Hieratic Seal of the Sun Dragon Servant",4,6,"66.67%"],"5336":[5336,"Hieratic Dragon King of Atum",2,3,"66.67%"],"1946719":[1946719,"Hieratic Dragon of Heka",2,4,"50.0%"],"1768966":[1768966,"Hieratic Dragon of Khonsu",2,4,"50.0%"],"10346":[10346,"Dark Ruler No More",1,2,"50.0%"],"5414":[5414,"Hieratic Seal of Reflection",1,3,"33.33%"],"9201":[9201,"Infinite Impermanence",16,39,"41.03%"],"12135":[12135,"Floowandereeze and the Dreaming Town",1,1,"100.0%"],"1310877":[1310877,"Aria Fey of Lune",1,3,"33.33%"],"2453922":[2453922,"Cheezbeast Piethon",1,4,"25.0%"],"2741861":[2741861,"Cheezbeast Cheeshire Cat",1,2,"50.0%"],"2439186":[2439186,"Cheezbeast Mozzarellaphant",1,4,"25.0%"],"2439162":[2439162,"Cheezbeast Bearger",3,5,"60.0%"],"8866":[8866,"Evenly Matched",8,11,"72.73%"],"11806":[11806,"Live☆Twin Sunny's Snitch",16,26,"61.54%"],"2521786":[2521786,"Cheese Dreams",2,5,"40.0%"],"11152":[11152,"Live☆Twin Lil-la",20,33,"60.61%"],"9189":[9189,"Called by the Grave",14,21,"66.67%"],"11527":[11527,"Live☆Twin Ki-sikil Frost",17,25,"68.0%"],"11154":[11154,"Evil★Twin Lil-la",25,33,"75.76%"],"2439753":[2439753,"Cheese Trap",1,4,"25.0%"],"4944":[4944,"Monster Reborn",6,7,"85.71%"],"11153":[11153,"Evil★Twin Ki-sikil",25,31,"80.65%"],"12112":[12112,"Evil★Twin's Trouble Sunny",24,27,"88.89%"],"1648879":[1648879,"Ray of Aria Fey",0,1,"0.0%"],"11810":[11810,"Ready Fusion",0,2,"0.0%"],"11782":[11782,"Allvain the Essence of Vanity",0,2,"0.0%"],"1648978":[1648978,"Aria Fey, Mistress of Change",0,1,"0.0%"],"9701":[9701,"Hiita the Fire Charmer, Ablaze",2,7,"28.57%"],"10345":[10345,"Nibiru, the Primal Being",12,18,"66.67%"],"11151":[11151,"Live☆Twin Ki-sikil",19,27,"70.37%"],"11156":[11156,"Live☆Twin Home",6,8,"75.0%"],"7590":[7590,"PSY-Framegear Gamma",3,9,"33.33%"],"11269":[11269,"Live☆Twin Lil-la Treat",15,17,"88.24%"],"2439751":[2439751,"Cheese Spell",2,6,"33.33%"],"2439167":[2439167,"Cheezbeast Pupperoni",2,4,"50.0%"],"10375":[10375,"Ghost Belle & Haunted Mansion",1,2,"50.0%"],"2439193":[2439193,"Cheezbeast Turtilla",3,5,"60.0%"],"2439168":[2439168,"Cheezbeast Baked Potatoad",2,3,"66.67%"],"1310876":[1310876,"Aria Fey of Day",1,1,"100.0%"],"1648901":[1648901,"Beam of Aria Fey",1,1,"100.0%"],"1648946":[1648946,"Aria Fey, Mistress of Ecology",1,1,"100.0%"],"1310880":[1310880,"Aria Fey, Mistress of Personality",1,1,"100.0%"],"7730":[7730,"Solemn Strike",6,7,"85.71%"],"8030":[8030,"Pot of Desires",11,15,"73.33%"],"2439175":[2439175,"Cheezbeast Frilled Cheese",2,5,"40.0%"],"11155":[11155,"Evil★Twins Ki-sikil & Lil-la",7,8,"87.5%"],"1978707":[1978707,"Infrastructure Web Wasp",5,8,"62.5%"],"2032168":[2032168,"Infrastructure Firewall Scanner",4,8,"50.0%"],"9879":[9879,"Cynet Mining",4,6,"66.67%"],"7318":[7318,"Wavering Eyes",2,2,"100.0%"],"2003112":[2003112,"Corrupted Infrastructure Ramblocker",5,7,"71.43%"],"2003099":[2003099,"Infrastructure Deltacraft",5,9,"55.56%"],"1993738":[1993738,"Infrastructure Digital Slicer",5,7,"71.43%"],"1996457":[1996457,"Infrastructure Gigabyte Stormbringer",5,9,"55.56%"],"1993875":[1993875,"Infrastructure Crazy Circuit Fortress",4,5,"80.0%"],"1993786":[1993786,"Infrastructure Dark Web Wild Wyvern",5,6,"83.33%"],"1996344":[1996344,"Assault on the Infrastructure",4,6,"66.67%"],"3344":[3344,"Pot of Duality",3,6,"50.0%"],"1765081":[1765081,"Net Terminal Gate",5,8,"62.5%"],"1764903":[1764903,"Net Terminal Genes - Memory",4,5,"80.0%"],"2003086":[2003086,"Infrastructure Morphchip",2,5,"40.0%"],"1764957":[1764957,"NTG Safeguard Cibo",3,5,"60.0%"],"4429":[4429,"Torrential Tribute",3,7,"42.86%"],"1764858":[1764858,"Net Terminal Genes - Replica",5,6,"83.33%"],"1978696":[1978696,"Infrastructure Data Raco",4,6,"66.67%"],"1978370":[1978370,"Infrastructure Data Decrypter",4,8,"50.0%"],"2333801":[2333801,"Silicon Creature Pcell",3,4,"75.0%"],"1764824":[1764824,"NTG Safeguard Sana",5,6,"83.33%"],"9261":[9261,"Lilith, Lady of Lament",4,4,"100.0%"],"2334069":[2334069,"NTG Safeguard Killy",5,5,"100.0%"],"8686":[8686,"Heavy Storm Duster",2,3,"66.67%"],"5839":[5839,"Sacred Sword of Seven Stars",1,3,"33.33%"],"2003041":[2003041,"Infrastructure Assault",3,4,"75.0%"],"2235450":[2235450,"Infrastructure Frenzy Hardware Dragon",1,1,"100.0%"],"4574":[4574,"Upstart Goblin",3,4,"75.0%"],"8482":[8482,"Lyrilusc - Turquoise Warbler",3,5,"60.0%"],"11921":[11921,"Lyrilusc - Beryl Canary",5,8,"62.5%"],"8441":[8441,"Lyrilusc - Recital Starling",5,6,"83.33%"],"2271577":[2271577,"Future Mech XX-Absolute - Xyz Emperor",5,6,"83.33%"],"1981445":[1981445,"R-Genex Gravitron",2,8,"25.0%"],"1981433":[1981433,"R-Genex Pipeline",2,6,"33.33%"],"2141426":[2141426,"Genex Jetron",2,8,"25.0%"],"1818":[1818,"Genex Blastfan",2,4,"50.0%"],"10868":[10868,"Forbidden Droplet",1,7,"14.29%"],"2452396":[2452396,"Genex Ally Tracer",2,7,"28.57%"],"11925":[11925,"Lyrilusc - Bird Call",5,7,"71.43%"],"8480":[8480,"Lyrilusc - Cobalt Sparrow",5,9,"55.56%"],"11922":[11922,"Lyrilusc - Celestine Wagtail",4,7,"57.14%"],"8511":[8511,"Lyrilusc - Assembled Nightingale",4,7,"57.14%"],"11926":[11926,"Lyrilusc - Bird Sanctuary",4,4,"100.0%"],"1933842":[1933842,"Dreadful Arsenal ZZ-ARES - Abyssal Flames",3,5,"60.0%"],"1205167":[1205167,"Danger!? Kikiyaon?",3,6,"50.0%"],"914":[914,"D.D. Crow",4,6,"66.67%"],"3443":[3443,"R-Genex Oracle",2,7,"28.57%"],"8481":[8481,"Lyrilusc - Sapphire Swallow",5,9,"55.56%"],"11923":[11923,"Lyrilusc - Ensemblue Robin",5,6,"83.33%"],"3445":[3445,"R-Genex Turbo",2,7,"28.57%"],"11924":[11924,"Lyrilusc - Promenade Thrush",2,2,"100.0%"],"1830":[1830,"Genex Undine",2,6,"33.33%"],"7587":[7587,"PSY-Frame Driver",4,10,"40.0%"],"1824":[1824,"Genex Power Planner",1,4,"25.0%"],"1981463":[1981463,"R-Genex Adjuster",2,6,"33.33%"],"1981837":[1981837,"R-Genex Capacitor",2,4,"50.0%"],"1981470":[1981470,"Genex Ally Recruiter",2,4,"50.0%"],"1819":[1819,"Genex Controller",2,5,"40.0%"],"7748":[7748,"Superheavy Samurai Swordmaster Musashi",2,4,"50.0%"],"6313":[6313,"Cyber Dragon Nova",1,2,"50.0%"],"7232":[7232,"Cyber Dragon Infinity",1,1,"100.0%"],"10461":[10461,"Desert Locusts",1,1,"100.0%"],"1859551":[1859551,"Akefalos Kavalaris",1,1,"100.0%"],"5528":[5528,"Foolish Burial",2,5,"40.0%"],"2385442":[2385442,"Shooting Star Dragon - Stardust Mirage",2,2,"100.0%"],"8381":[8381,"Foolish Burial Goods",1,2,"50.0%"],"21714":[21714,"Construction of the Antrap's Nest",1,2,"50.0%"],"21686":[21686,"Antrap Abdomen",3,6,"50.0%"],"21697":[21697,"The Antrap's Nest",3,5,"60.0%"],"585307":[585307,"Antrap Pedipalps",2,5,"40.0%"],"21669":[21669,"Antrap Antenna",1,2,"50.0%"],"21652":[21652,"Antrap Tarsus",3,5,"60.0%"],"21570":[21570,"Antrap Mandible L",3,4,"75.0%"],"21585":[21585,"Antrap Maxilla",3,4,"75.0%"],"2417757":[2417757,"Starbreeze Ringmaster’s Selection!",1,2,"50.0%"],"2429549":[2429549,"Starbreeze Ringmaster's Coronation!",1,3,"33.33%"],"2422925":[2422925,"Joyful Gift-Giver, Panera",1,5,"20.0%"],"5671":[5671,"Fire Formation - Tenki",0,3,"0.0%"],"2258346":[2258346,"Ivory-Clad Proposer, Panera",1,4,"25.0%"],"1926227":[1926227,"Nimnim, Scientist Of Wavering Winds",0,1,"0.0%"],"21724":[21724,"Collapse of the Antrap's Nest",2,2,"100.0%"],"1999462":[1999462,"Panera The Beachside Enjoyer",1,3,"33.33%"],"2258338":[2258338,"Starbreeze Wedding Hoop!",1,3,"33.33%"],"2417736":[2417736,"Starbreeze Beast-Tamer's Grand Entrance!",1,2,"50.0%"],"2258333":[2258333,"Ringmaster-In-Training, Panera",1,4,"25.0%"],"2422849":[2422849,"Panera & Zela, Romantic Whitewind Brides",0,2,"0.0%"],"79359":[79359,"Coronation of the Antrap's Nest",3,4,"75.0%"],"2417734":[2417734,"Starbreeze Partnership!",0,2,"0.0%"],"21676":[21676,"Antrap Thorax",2,4,"50.0%"],"96006":[96006,"Antrap Stinger",3,5,"60.0%"],"21662":[21662,"Antrap Oculars",3,4,"75.0%"],"21579":[21579,"Antrap Mandible R",2,2,"100.0%"],"10056":[10056,"Wynn the Wind Charmer, Verdant",0,2,"0.0%"],"7175":[7175,"Ghost Ogre & Snow Rabbit",1,2,"50.0%"],"2429571":[2429571,"Starbreeze Beast-Tamer’s Purplish Pastel!",0,1,"0.0%"],"11327":[11327,"Apollousa, Bow of the Goddess",1,2,"50.0%"],"251958":[251958,"Confusion of the Antrap's Nest",1,3,"33.33%"],"10022":[10022,"Tenyi Spirit - Adhara",5,8,"62.5%"],"10053":[10053,"Monk of the Tenyi",3,5,"60.0%"],"10069":[10069,"Vessel for the Dragon Cycle",3,6,"50.0%"],"12065":[12065,"Swordsoul of Taia",6,9,"66.67%"],"12102":[12102,"Swordsoul Grandmaster - Chixiao",6,9,"66.67%"],"10213":[10213,"Tenyi Spirit - Ashuna",3,7,"42.86%"],"12114":[12114,"Swordsoul Emergence",5,9,"55.56%"],"12066":[12066,"Swordsoul Strategist Longyuan",5,7,"71.43%"],"11917":[11917,"Baronne de Fleur",1,2,"50.0%"],"10026":[10026,"Tenyi Spirit - Vishuda",4,7,"57.14%"],"2358621":[2358621,"Dance of Swords, Kousetsu",1,2,"50.0%"],"2358610":[2358610,"Dance of Swords, Imanotsurugi",1,2,"50.0%"],"2358747":[2358747,"Dance of Swords Omen",1,3,"33.33%"],"2358634":[2358634,"Dance of Swords, Shishiou",1,3,"33.33%"],"2358626":[2358626,"Dance of Swords, Souza",1,1,"100.0%"],"930175":[930175,"Fatal Fallen Funk Fish Feeding",1,1,"100.0%"],"2358686":[2358686,"Dance of Swords, Yamabushi",1,2,"50.0%"],"1177845":[1177845,"Bubble Dragon",1,1,"100.0%"],"2680571":[2680571,"Dance of Swords, Kasen",1,2,"50.0%"],"2680642":[2680642,"Dance of Swords, Mutsunokami",1,2,"50.0%"],"12068":[12068,"Incredible Ecclesia, the Virtuous",3,6,"50.0%"],"1940":[1940,"Gold Sarcophagus",3,5,"60.0%"],"6520":[6520,"Artifact Lancea",1,4,"25.0%"],"2658416":[2658416,"Dance of Swords Majesty Days",0,1,"0.0%"],"2658389":[2658389,"Dance of Swords Formation",0,1,"0.0%"],"2358638":[2358638,"Dance of Swords, Mikazuki",0,1,"0.0%"],"1331165":[1331165,"Torrent Kraken",0,1,"0.0%"],"6537":[6537,"Baxia, Brightness of the Yang Zing",1,3,"33.33%"],"2658366":[2658366,"Dance of Swords, Iwatooshi",0,1,"0.0%"],"1649898":[1649898,"Ib, World Chalice's Reincarnation",0,1,"0.0%"],"10676":[10676,"Adamancipator Risen - Dragite",0,1,"0.0%"],"2197535":[2197535,"Nauticorpse, Necroswain",7,9,"77.78%"],"2211850":[2211850,"Nauticorpse Black Spot",7,9,"77.78%"],"2195414":[2195414,"Nauticorpse, Necrosail",7,13,"53.85%"],"2195442":[2195442,"Nauticorpse, Necroneer",7,10,"70.0%"],"2211793":[2211793,"Nauticorpse Set Sailing",6,11,"54.55%"],"1611198":[1611198,"Dismal Backwater",2,5,"40.0%"],"1623302":[1623302,"Darkwater Fishook",3,6,"50.0%"],"1623184":[1623184,"Darkwater Cuttershark",6,9,"66.67%"],"2211914":[2211914,"Nauticorpse Voyage!",3,9,"33.33%"],"1623151":[1623151,"Darkwater Wheelback",5,8,"62.5%"],"1623160":[1623160,"Darkwater Penrod",4,7,"57.14%"],"2211875":[2211875,"Nauticorpse Hempen Curse",7,11,"63.64%"],"2211771":[2211771,"Nauticorpse, Necrocaptain",6,8,"75.0%"],"1610982":[1610982,"Drowned Secrets of the Abyss",5,7,"71.43%"],"2609533":[2609533,"Watery Grave",2,3,"66.67%"],"1623170":[1623170,"Darkwater Angler",5,8,"62.5%"],"2217366":[2217366,"Nauticorpse Old Salt",3,6,"50.0%"],"2221740":[2221740,"Nauticorpse Chase Gun",2,2,"100.0%"],"8029":[8029,"Cosmic Cyclone",3,5,"60.0%"],"8257":[8257,"Dimensional Barrier",1,4,"25.0%"],"1623316":[1623316,"Darkwater Maliceel",5,7,"71.43%"],"3913":[3913,"Solemn Judgment",7,13,"53.85%"],"2197564":[2197564,"Nauticorpse, Necrobooter",2,5,"40.0%"],"82":[82,"Allure of Darkness",8,11,"72.73%"],"6895":[6895,"Dark Contract with the Gate",5,7,"71.43%"],"7471":[7471,"D/D Swirl Slime",5,7,"71.43%"],"7805":[7805,"D/D Lamia",6,8,"75.0%"],"6893":[6893,"D/D/D Flame King Genghis",6,7,"85.71%"],"7081":[7081,"D/D/D Oblivion King Abyss Ragnarok",5,6,"83.33%"],"7801":[7801,"D/D/D Chaos King Apocalypse",5,5,"100.0%"],"6894":[6894,"D/D/D Gust King Alexander",6,6,"100.0%"],"6896":[6896,"Dark Contract with the Swamp King",5,7,"71.43%"],"7439":[7439,"Odd-Eyes Meteorburst Dragon",1,1,"100.0%"],"10424":[10424,"Cross-Sheep",5,5,"100.0%"],"8570":[8570,"D/D/D Flame High King Genghis",6,7,"85.71%"],"7809":[7809,"D/D/D Cursed King Siegfried",6,7,"85.71%"],"7901":[7901,"Crystal Wing Synchro Dragon",6,6,"100.0%"],"9767":[9767,"D/D/D Abyss King Gilgamesh",5,6,"83.33%"],"7803":[7803,"D/D Savant Copernicus",3,4,"75.0%"],"1816306":[1816306,"D/D Shadow",5,7,"71.43%"],"1658836":[1658836,"D/D/D Abyssal Doom King Soulomon",5,6,"83.33%"],"8652":[8652,"D/D/D Wave High King Caesar",5,5,"100.0%"],"6891":[6891,"D/D Savant Kepler",6,7,"85.71%"],"1992353":[1992353,"Withering Cocoon",1,5,"20.0%"],"10138":[10138,"Battlewasp - Sting the Poison",3,7,"42.86%"],"10865":[10865,"Triple Tactics Talent",4,7,"57.14%"],"10139":[10139,"Battlewasp - Twinbow the Attacker",4,8,"50.0%"],"12220":[12220,"Beetrooper Scout Buggy",4,6,"66.67%"],"9069":[9069,"Inzektor Picofalena",4,8,"50.0%"],"10140":[10140,"Battlewasp - Arbalest the Rapidfire",1,3,"33.33%"],"6525":[6525,"Resonance Insect",4,6,"66.67%"],"12228":[12228,"Beetrooper Armor Horn",4,6,"66.67%"],"1219":[1219,"Doom Dozer",4,7,"57.14%"],"9495":[9495,"Gokipole",4,7,"57.14%"],"9638":[9638,"Danger! Mothman!",1,2,"50.0%"],"1870":[1870,"Girochin Kuwagata",4,5,"80.0%"],"3212":[3212,"One for One",3,4,"75.0%"],"12229":[12229,"Giant Beetrooper Invincible Atlas",4,6,"66.67%"],"3833":[3833,"Silent Insect",0,1,"0.0%"],"11111":[11111,"Jack-In-The-Hand",3,3,"100.0%"],"7472":[7472,"D/D Necro Slime",5,5,"100.0%"],"8980":[8980,"Contact \"C\"",1,2,"50.0%"],"12227":[12227,"Beetrooper Sting Lancer",4,7,"57.14%"],"11158":[11158,"Secret Password",11,18,"61.11%"],"2457468":[2457468,"Fossilrai Yasukadon",0,1,"0.0%"],"9171":[9171,"Knightmare Unicorn",9,9,"100.0%"],"10239":[10239,"Unchained Abomination",7,7,"100.0%"],"2457514":[2457514,"Fossilrai Emperor's Castle",0,2,"0.0%"],"304":[304,"Babycerasaurus",0,1,"0.0%"],"2459592":[2459592,"Fossilrai Spirit",0,1,"0.0%"],"6152":[6152,"Survival of the Fittest",0,1,"0.0%"],"2460634":[2460634,"Fossilrai Straw Doll",0,1,"0.0%"],"2451619":[2451619,"Fossilrai Fūmamastax",0,2,"0.0%"],"3875":[3875,"Skull Meister",2,2,"100.0%"],"10136":[10136,"Battlewasp - Pin the Bullseye",3,7,"42.86%"],"8573":[8573,"Petiteranodon",0,2,"0.0%"],"10244":[10244,"Seraphim Papillion",4,4,"100.0%"],"12230":[12230,"Beetrooper Formation",3,5,"60.0%"],"10959":[10959,"Number 3: Cicada King",2,3,"66.67%"],"8575":[8575,"Souleating Oviraptor",0,1,"0.0%"],"8738":[8738,"Double Evolution Pill",0,1,"0.0%"],"8574":[8574,"Ultimate Conductor Tyranno",0,1,"0.0%"],"528":[528,"Book of Moon",3,6,"50.0%"],"7756":[7756,"Gameciel, the Sea Turtle Kaiju",1,4,"25.0%"],"11159":[11159,"Evil★Twin Challenge",2,5,"40.0%"],"1372872":[1372872,"Mitori Geiko",2,2,"100.0%"],"1978775":[1978775,"Corrupted Infrastructure CraZ Cougar",0,2,"0.0%"],"2306224":[2306224,"Conflagrant Hero Leo",3,7,"42.86%"],"2305803":[2305803,"Conflagrant Crafter Jack",3,8,"37.5%"],"2308793":[2308793,"Conflagrant Future Rider",1,3,"33.33%"],"2306343":[2306343,"Conflagrant Twin Gear",3,9,"33.33%"],"2308733":[2308733,"Conflagrant Bonnie Mech",3,4,"75.0%"],"2306455":[2306455,"Conflagrant Rider Motor",3,6,"50.0%"],"2307723":[2307723,"Conflagrant Winged Squad",4,6,"66.67%"],"2307797":[2307797,"Ignescent Gear Assemble",3,6,"50.0%"],"2306269":[2306269,"Conflagrant General Rubis",3,4,"75.0%"],"2307645":[2307645,"Conflagrant Gear Leader",3,8,"37.5%"],"2307853":[2307853,"Conflagrant Fighter Joyo",2,3,"66.67%"],"2308250":[2308250,"Conflagrant Captain Joyo",2,2,"100.0%"],"2310483":[2310483,"Ignescent Barrage",3,3,"100.0%"],"2742232":[2742232,"Conflagrant Lone Drake",1,2,"50.0%"],"2505107":[2505107,"Conflagrant Motor Ace",1,1,"100.0%"],"12130":[12130,"Small World",0,3,"0.0%"],"1340":[1340,"Effect Veiler",4,8,"50.0%"],"2505088":[2505088,"Conflagrant Future Ace",2,4,"50.0%"],"2472715":[2472715,"Conflagrant Soul Joyo",1,5,"20.0%"],"2272":[2272,"Instant Fusion",2,4,"50.0%"],"2315782":[2315782,"Minute Feathered Serpent",1,1,"100.0%"],"1948813":[1948813,"Songs of Aria Fey",1,1,"100.0%"],"2439197":[2439197,"Cheezbeast Mascarpony",1,2,"50.0%"],"1432":[1432,"Emergency Teleport",0,2,"0.0%"],"10869":[10869,"Heavenly Dragon Circle",0,1,"0.0%"],"8452":[8452,"Harpie's Feather Storm",1,2,"50.0%"],"11323":[11323,"Droll & Lock Bird",2,7,"28.57%"],"10568":[10568,"Archnemeses Protos",3,4,"75.0%"],"12134":[12134,"Swordsoul Blackout",2,4,"50.0%"],"8886":[8886,"Linkuriboh",1,2,"50.0%"],"10023":[10023,"Tenyi Spirit - Shthana",3,5,"60.0%"],"2387841":[2387841,"Mathmech Vector",0,1,"0.0%"],"1770162":[1770162,"Number 129: Lost Chained Dragon",1,1,"100.0%"],"1573":[1573,"Fiendish Chain",1,1,"100.0%"],"12115":[12115,"Swordsoul Sacred Summit",2,5,"40.0%"],"10882":[10882,"Ice Dragon's Prison",4,8,"50.0%"],"9543":[9543,"Trap Trick",6,11,"54.55%"],"2201621":[2201621,"R'lyeh, Prison City of the Old One",1,1,"100.0%"],"11629":[11629,"I:P Masquerena",1,2,"50.0%"],"3441":[3441,"R-Genex Crusher",1,4,"25.0%"],"1764999":[1764999,"Net Terminal Genes - Vanish",4,4,"100.0%"],"3859":[3859,"Skill Drain",1,1,"100.0%"],"430":[430,"Black Rose Dragon",0,1,"0.0%"],"7718":[7718,"Twin Twisters",0,3,"0.0%"],"2875":[2875,"Mind Control",0,1,"0.0%"],"1551870":[1551870,"Exquisite Knowledge",1,1,"100.0%"],"10188":[10188,"Five-Headed Dragon",1,1,"100.0%"],"332":[332,"Barrier Statue of the Stormwinds",4,4,"100.0%"],"4235":[4235,"Terraforming",0,2,"0.0%"],"10873":[10873,"Dogmatika Punishment",0,1,"0.0%"],"7410":[7410,"Elder Entity N'tss",0,1,"0.0%"],"7299":[7299,"D/D/D Oracle King d'Arc",2,3,"66.67%"],"79412":[79412,"Colossus of the Antrap's Nest",0,2,"0.0%"],"5505":[5505,"Where Arf Thou?",1,2,"50.0%"],"2308836":[2308836,"Emergency Ignite Gear Squad",1,4,"25.0%"],"12103":[12103,"Swordsoul Supreme Sovereign - Chengying",1,1,"100.0%"],"10444":[10444,"Lightning Storm",1,6,"16.67%"],"10054":[10054,"Shaman of the Tenyi",1,1,"100.0%"],"7510":[7510,"D/D/D Duo-Dawn King Kali Yuga",1,1,"100.0%"],"7755":[7755,"Radian, the Multidimensional Kaiju",1,2,"50.0%"],"10344":[10344,"Dimension Shifter",1,2,"50.0%"],"1267999":[1267999,"Vapor Saucer",1,1,"100.0%"],"2439170":[2439170,"Cheezbeast Pizzasaurus",0,1,"0.0%"],"2402028":[2402028,"Imperialis Odia",1,1,"100.0%"],"2401988":[2401988,"Imperialis Vindicta",0,1,"0.0%"],"5333":[5333,"Hieratic Dragon of Tefnuit",4,5,"80.0%"],"1944778":[1944778,"Hieratic Dragon King of Hor",3,3,"100.0%"],"12136":[12136,"Floowandereeze and the Scary Sea",1,1,"100.0%"],"7552":[7552,"Kumongous, the Sticky String Kaiju",2,5,"40.0%"],"12231":[12231,"Beetrooper Fly & Sting",1,2,"50.0%"],"6926":[6926,"Primitive Butterfly",2,4,"50.0%"],"7851":[7851,"Interrupted Kaiju Slumber",1,1,"100.0%"],"1818903":[1818903,"Ghost Wheel & Floating Lanterns",1,1,"100.0%"],"7849":[7849,"Gadarla, the Mystery Dust Kaiju",1,3,"33.33%"],"12120":[12120,"Floowandereeze and the Unexplored Winds",1,1,"100.0%"],"12226":[12226,"Beetrooper Scale Bomber",0,1,"0.0%"],"8751":[8751,"Link Disciple",0,1,"0.0%"],"9315":[9315,"Link Devotee",0,1,"0.0%"],"1718677":[1718677,"Ferwilder Tarr",3,4,"75.0%"],"9875":[9875,"Mekk-Knight Crusadia Avramax",0,1,"0.0%"],"1642313":[1642313,"Rooftop Inu",2,3,"66.67%"],"1623225":[1623225,"Omen of the Depths",2,2,"100.0%"],"1479910":[1479910,"Swift Archer Lumis",1,1,"100.0%"],"2106800":[2106800,"Number 198: Antidote Assaulter",0,1,"0.0%"],"12091":[12091,"Lord of the Heavenly Prison",1,2,"50.0%"],"9328":[9328,"Wee Witch's Apprentice",0,1,"0.0%"],"5338":[5338,"Hieratic Seal of Convocation",1,2,"50.0%"],"5328":[5328,"Hieratic Seal of the Sun Dragon Overlord",1,2,"50.0%"],"1949247":[1949247,"Hieratic Dragon Prince of Thoth",1,1,"100.0%"],"8536":[8536,"Dark Contract with the Eternal Darkness",1,1,"100.0%"],"10596":[10596,"Ghost Mourner & Moonlit Chill",1,1,"100.0%"],"10229":[10229,"Draco Berserker of the Tenyi",1,2,"50.0%"],"1103224":[1103224,"Majesdraco of Wavering Winds",1,1,"100.0%"],"9814":[9814,"Salamangreat Almiraj",1,3,"33.33%"],"1884551":[1884551,"Panera the Dazzling Ringmaster",1,1,"100.0%"],"12092":[12092,"Fengli the Soldrapom",1,1,"100.0%"],"2417774":[2417774,"Panera Carnivale, Starbreeze Showstopper",1,1,"100.0%"],"10296":[10296,"Geomathmech Final Sigma",0,1,"0.0%"],"1607460":[1607460,"Tokyo Terror - Atomic Blast!",2,2,"100.0%"],"1607463":[1607463,"Tokyo Terror - A Beast's Awakening",1,1,"100.0%"],"1607465":[1607465,"Evolution of the Scaled Menace",2,3,"66.67%"],"1736029":[1736029,"Lost Wind's Cyclone",1,1,"100.0%"],"1673":[1673,"Fossil Dig",1,1,"100.0%"],"1607436":[1607436,"Tokyo Terror - Kamata Kun",2,3,"66.67%"],"1607444":[1607444,"Tokyo Terror - Shinagawa Kun",2,3,"66.67%"],"1607473":[1607473,"Tokyo Terror - Threat at Hand",2,3,"66.67%"],"1607455":[1607455,"Tokyo Terror - Shin Gojira",2,2,"100.0%"],"1956889":[1956889,"Shadow of the Reaper",2,2,"100.0%"],"1607481":[1607481,"Tokyo Terror - Adaptation",0,1,"0.0%"],"1765072":[1765072,"Net Terminal Genes - Reboot",1,1,"100.0%"],"4092":[4092,"Summon Limit",1,1,"100.0%"],"1956894":[1956894,"Blessings of the Doomed",1,1,"100.0%"],"8942":[8942,"Kikinagashi Fucho",0,1,"0.0%"],"1447":[1447,"Enemy Controller",1,3,"33.33%"],"1787160":[1787160,"Darkwater Cthullord",1,2,"50.0%"],"2603826":[2603826,"Fiendish Raven",1,1,"100.0%"],"1599951":[1599951,"Spawn of Exile",2,2,"100.0%"],"2402044":[2402044,"Imperialis Ascendance",0,1,"0.0%"],"2405675":[2405675,"Imperialis Prominence",0,1,"0.0%"]}